{
	"v001-55": {
		"size": [
			{
				"type": "duration",
				"size": "14:15"
			}
		]
	},
	"v001-54": {
		"size": [
			{
				"type": "duration",
				"size": "11:33"
			}
		]
	},
	"v001-52": {
		"size": [
			{
				"type": "duration",
				"size": "08:27"
			}
		]
	},
    "001-01": {
        "related": [
            {
                "name": "v001-07",
                "type": "video"
            }
        ],
        "size": [
            {
                "size": 152,
                "type": "images"
            }
        ]
    },
    "001-02": {
        "related": [
            {
                "name": "v001-08",
                "type": "video"
            }
        ],
        "size": [
            {
                "size": 164,
                "type": "images"
            }
        ]
    },
    "001-03": {
        "size": [
            {
                "size": 70,
                "type": "images"
            }
        ]
    },
    "001-04": {
        "size": [
            {
                "size": 91,
                "type": "images"
            }
        ]
    },
    "001-05": {
        "related": [
            {
                "name": "v001-16",
                "type": "video"
            }
        ],
        "size": [
            {
                "size": 168,
                "type": "images"
            }
        ]
    },
    "001-06": {
        "related": [
            {
                "name": "v001-17",
                "type": "video"
            }
        ],
        "size": [
            {
                "size": 218,
                "type": "images"
            }
        ]
    },
    "001-07": {
        "related": [
            {
                "name": "v001-18",
                "type": "video"
            }
        ],
        "size": [
            {
                "size": 102,
                "type": "images"
            }
        ]
    },
    "001-08": {
        "size": [
            {
                "size": 81,
                "type": "images"
            }
        ]
    },
    "001-09": {
        "related": [
            {
                "name": "v001-25",
                "type": "video"
            }
        ],
        "size": [
            {
                "size": 152,
                "type": "images"
            }
        ]
    },
    "001-10": {
        "related": [
            {
                "name": "v001-31",
                "type": "video"
            }
        ],
        "size": [
            {
                "size": 157,
                "type": "images"
            }
        ]
    },
    "002-01": {
        "related": [
            {
                "name": "v01-27",
                "type": "video"
            }
        ],
        "size": [
            {
                "size": 292,
                "type": "images"
            }
        ]
    },
    "002-02": {
        "related": [
            {
                "name": "v001-28",
                "type": "video"
            }
        ],
        "size": [
            {
                "size": 202,
                "type": "images"
            }
        ]
    },
    "002-03": {
        "related": [
            {
                "name": "v001-34",
                "type": "video"
            }
        ],
        "size": [
            {
                "size": 209,
                "type": "images"
            }
        ]
    },
    "002-04": {
        "related": [
            {
                "name": "v001-23",
                "type": "video"
            }
        ],
        "size": [
            {
                "size": 123,
                "type": "images"
            }
        ]
    },
    "002-05": {
        "size": [
            {
                "size": 150,
                "type": "images"
            }
        ]
    },
    "002-06": {
        "related": [
            {
                "name": "v001-40",
                "type": "video"
            }
        ],
        "size": [
            {
                "size": 104,
                "type": "images"
            }
        ]
    },
    "002-07": {
        "related": [
            {
                "name": "v001-37",
                "type": "video"
            }
        ],
        "size": [
            {
                "size": 245,
                "type": "images"
            }
        ]
    },
    "002-08": {
        "related": [
            {
                "name": "v01-33",
                "type": "video"
            }
        ],
        "size": [
            {
                "size": 251,
                "type": "images"
            }
        ]
    },
    "002-09": {
        "related": [
            {
                "name": "v001-35",
                "type": "video"
            }
        ],
        "size": [
            {
                "size": 260,
                "type": "images"
            }
        ]
    },
    "002-10": {
        "related": [
            {
                "name": "v001-38",
                "type": "video"
            }
        ],
        "size": [
            {
                "size": 233,
                "type": "images"
            }
        ]
    },
    "003-01": {
        "related": [
            {
                "name": "v001-42",
                "type": "video"
            }
        ],
        "size": [
            {
                "size": 156,
                "type": "images"
            }
        ]
    },
    "003-02": {
        "related": [
            {
                "name": "v001-39",
                "type": "video"
            }
        ],
        "size": [
            {
                "size": 154,
                "type": "images"
            }
        ]
    },
    "v001-01": {
        "size": [
            {
                "size": "18:04",
                "type": "duration"
            }
        ]
    },
    "v001-02": {
        "size": [
            {
                "size": "15:10",
                "type": "duration"
            }
        ]
    },
    "v001-03": {
        "size": [
            {
                "size": "15:59",
                "type": "duration"
            }
        ]
    },
    "v001-04": {
        "size": [
            {
                "size": "16:58",
                "type": "duration"
            }
        ]
    },
    "v001-05": {
        "size": [
            {
                "size": "12:47",
                "type": "duration"
            }
        ]
    },
    "v001-06": {
        "size": [
            {
                "size": "10:18",
                "type": "duration"
            }
        ]
    },
    "v001-07": {
        "related": [
            {
                "name": "001-01",
                "type": "photo"
            }
        ],
        "size": [
            {
                "size": "15:01",
                "type": "duration"
            }
        ]
    },
    "v001-08": {
        "related": [
            {
                "name": "001-02",
                "type": "photo"
            }
        ],
        "size": [
            {
                "size": "10:06",
                "type": "duration"
            }
        ]
    },
    "v001-09": {
        "size": [
            {
                "size": "12:41",
                "type": "duration"
            }
        ]
    },
    "v001-10": {
        "size": [
            {
                "size": "14:40",
                "type": "duration"
            }
        ]
    },
    "v001-11": {
        "size": [
            {
                "size": "14:37",
                "type": "duration"
            }
        ]
    },
    "v001-12": {
        "size": [
            {
                "size": "15:56",
                "type": "duration"
            }
        ]
    },
    "v001-13": {
        "size": [
            {
                "size": "7:55",
                "type": "duration"
            }
        ]
    },
    "v001-14": {
        "size": [
            {
                "size": "11:37",
                "type": "duration"
            }
        ]
    },
    "v001-15": {
        "size": [
            {
                "size": "12:26",
                "type": "duration"
            }
        ]
    },
    "v001-16": {
        "related": [
            {
                "name": "001-05",
                "type": "photo"
            }
        ],
        "size": [
            {
                "size": "11:18",
                "type": "duration"
            }
        ]
    },
    "v001-17": {
        "related": [
            {
                "name": "001-06",
                "type": "photo"
            }
        ],
        "size": [
            {
                "size": "12:11",
                "type": "duration"
            }
        ]
    },
    "v001-18": {
        "related": [
            {
                "name": "001-07",
                "type": "photo"
            }
        ],
        "size": [
            {
                "size": "8:26",
                "type": "duration"
            }
        ]
    },
    "v001-19": {
        "size": [
            {
                "size": "10:15",
                "type": "duration"
            }
        ]
    },
    "v001-20": {
        "size": [
            {
                "size": "13:06",
                "type": "duration"
            }
        ]
    },
    "v001-21": {
        "size": [
            {
                "size": "20:43",
                "type": "duration"
            }
        ]
    },
    "v001-23": {
        "related": [
            {
                "name": "002-04",
                "type": "photo"
            }
        ],
        "size": [
            {
                "size": "9:04",
                "type": "duration"
            }
        ]
    },
    "v001-24": {
        "size": [
            {
                "size": "14:16",
                "type": "duration"
            }
        ]
    },
    "v001-25": {
        "related": [
            {
                "name": "001-09",
                "type": "photo"
            }
        ],
        "size": [
            {
                "size": "9:18",
                "type": "duration"
            }
        ]
    },
    "v001-26": {
        "size": [
            {
                "size": "8:18",
                "type": "duration"
            }
        ]
    },
    "v001-28": {
        "related": [
            {
                "name": "002-02",
                "type": "photo"
            }
        ],
        "size": [
            {
                "size": "6:20",
                "type": "duration"
            }
        ]
    },
    "v001-29": {
        "size": [
            {
                "size": "7:19",
                "type": "duration"
            }
        ]
    },
    "v001-30": {
        "size": [
            {
                "size": "15:15",
                "type": "duration"
            }
        ]
    },
    "v001-31": {
        "related": [
            {
                "name": "001-10",
                "type": "photo"
            }
        ],
        "size": [
            {
                "size": "7:58",
                "type": "duration"
            }
        ]
    },
    "v001-32": {
        "size": [
            {
                "size": "13:59",
                "type": "duration"
            }
        ]
    },
    "v001-34": {
        "related": [
            {
                "name": "002-03",
                "type": "photo"
            }
        ],
        "size": [
            {
                "size": "14:03",
                "type": "duration"
            }
        ]
    },
    "v001-35": {
        "related": [
            {
                "name": "002-09",
                "type": "photo"
            }
        ],
        "size": [
            {
                "size": "12:55",
                "type": "duration"
            }
        ]
    },
    "v001-36": {
        "size": [
            {
                "size": "10:02",
                "type": "duration"
            }
        ]
    },
    "v001-37": {
        "related": [
            {
                "name": "002-07",
                "type": "photo"
            }
        ],
        "size": [
            {
                "size": "12:29",
                "type": "duration"
            }
        ]
    },
    "v001-38": {
        "related": [
            {
                "name": "002-10",
                "type": "photo"
            }
        ],
        "size": [
            {
                "size": "10:41",
                "type": "duration"
            }
        ]
    },
    "v001-39": {
        "related": [
            {
                "name": "003-02",
                "type": "photo"
            }
        ],
        "size": [
            {
                "size": "11:28",
                "type": "duration"
            }
        ]
    },
    "v001-40": {
        "related": [
            {
                "name": "002-06",
                "type": "photo"
            }
        ],
        "size": [
            {
                "size": "07:04",
                "type": "duration"
            }
        ]
    },
    "v001-41": {
        "size": [
            {
                "size": "11:46",
                "type": "duration"
            }
        ]
    },
    "v001-42": {
        "related": [
            {
                "name": "003-01",
                "type": "photo"
            }
        ],
        "size": [
            {
                "size": "07:37",
                "type": "duration"
            }
        ]
    },
    "v001-43": {
        "size": [
            {
                "size": "15:49",
                "type": "duration"
            }
        ]
    },
    "v001-44": {
        "size": [
            {
                "size": "11:01",
                "type": "duration"
            }
        ]
    },
    "v001-45": {
        "size": [
            {
                "size": "14:27",
                "type": "duration"
            }
        ]
    },
    "v001-46": {
        "size": [
            {
                "size": "07:29",
                "type": "duration"
            }
        ]
    },
    "v001-47": {
        "size": [
            {
                "size": "11:43",
                "type": "duration"
            }
        ]
    },
    "v001-48": {
        "size": []
    },
    "v001-49": {
        "size": [
            {
                "size": "14:03",
                "type": "duration"
            }
        ]
    },
    "v001-50": {
        "size": [
            {
                "size": "13:39",
                "type": "duration"
            }
        ]
    },
    "v001-51": {
        "size": [
            {
                "size": "08:44",
                "type": "duration"
            }
        ]
    },
    "v001-53": {
        "size": [
            {
                "size": "13:31",
                "type": "duration"
            }
        ]
    },
    "v01-22": {
        "size": [
            {
                "size": "15:51",
                "type": "duration"
            }
        ]
    },
    "v01-27": {
        "related": [
            {
                "name": "002-01",
                "type": "photo"
            }
        ],
        "size": [
            {
                "size": "9:59",
                "type": "duration"
            }
        ]
    },
    "v01-33": {
        "related": [
            {
                "name": "002-08",
                "type": "photo"
            }
        ],
        "size": [
            {
                "size": "9:11",
                "type": "duration"
            }
        ]
    }
}
